pathgenmap/__init__.py
pathgenmap/pathgenmap.py
pathgenmap/pathprocess.py
pathgenmap-0.1.3.dist-info/LICENSE
pathgenmap-0.1.3.dist-info/METADATA
pathgenmap-0.1.3.dist-info/WHEEL
pathgenmap-0.1.3.dist-info/entry_points.txt
pathgenmap-0.1.3.dist-info/top_level.txt
pathgenmap-0.1.3.dist-info/RECORD
